pytest_dryci/__init__.py
pytest_dryci/plugin.py
pytest_dryci-0.1.1.data/scripts/repo_dagger
pytest_dryci-0.1.1.dist-info/METADATA
pytest_dryci-0.1.1.dist-info/WHEEL
pytest_dryci-0.1.1.dist-info/entry_points.txt
pytest_dryci-0.1.1.dist-info/RECORD
