Metadata-Version: 2.3
Name: pytest-dryci
Version: 0.1.1
Summary: Test caching plugin for pytest
Project-URL: Homepage, https://github.com/Wazzaps/dryci
Project-URL: Repository, https://github.com/Wazzaps/dryci.git
Project-URL: Issues, https://github.com/Wazzaps/dryci/issues
Author-email: David Shlemayev <david.shlemayev@gmail.com>
License-Expression: MIT
Classifier: Development Status :: 4 - Beta
Classifier: Framework :: Pytest
Classifier: Intended Audience :: Developers
Classifier: License :: OSI Approved :: MIT License
Classifier: Programming Language :: Python :: 3
Classifier: Programming Language :: Python :: 3.8
Classifier: Topic :: Software Development :: Testing
Requires-Python: >=3.8
